df2img-0.2.21.dist-info/METADATA
df2img-0.2.21.dist-info/WHEEL
df2img-0.2.21.dist-info/entry_points.txt
df2img-0.2.21.dist-info/licenses/LICENSE
df2img/__init__.py
df2img/main.py
df2img/py.typed
df2img-0.2.21.dist-info/RECORD
