Metadata-Version: 2.1
Name: df2img
Version: 0.2.21
Summary: Save a Pandas DataFrame as image
Keywords: pandas,dataframe,image
Author-Email: Andreas Vester <info@df2img.dev>
License: MIT License
Classifier: Development Status :: 4 - Beta
Classifier: Programming Language :: Python
Classifier: Operating System :: OS Independent
Classifier: Topic :: Software Development :: Libraries :: Python Modules
Classifier: Programming Language :: Python :: 3
Classifier: Programming Language :: Python :: 3.9
Classifier: Programming Language :: Python :: 3.10
Classifier: Programming Language :: Python :: 3.11
Classifier: Programming Language :: Python :: 3.12
Project-URL: BugTracker, https://github.com/andreas-vester/df2img/issues?q=label%3Abug+
Project-URL: homepage, https://df2img.dev
Project-URL: repository, https://github.com/andreas-vester/df2img
Project-URL: documentation, https://df2img.dev
Requires-Python: >=3.9
Requires-Dist: kaleido==0.2.1; platform_system != "Windows"
Requires-Dist: kaleido==0.1.0post1; platform_system == "Windows"
Requires-Dist: pandas<3.0.0
Requires-Dist: plotly
Requires-Dist: ipython
Requires-Dist: nbformat
